{
  "book": 5,
  "card": 1,
  "lines": [
    1,
    73
  ],
  "title_latin": null,
  "title_english": null,
  "text": [
    {
      "n": 1,
      "latin": "Dumque ea Cephenum medio Danaeius heros"
    },
    {
      "n": 2,
      "latin": "agmine commemorat, fremida regalia turba"
    },
    {
      "n": 3,
      "latin": "atria complentur: nec coniugialia festa"
    },
    {
      "n": 4,
      "latin": "qui canat est clamor, sed qui fera nuntiet arma."
    },
    {
      "n": 5,
      "latin": "Inque repentinos convivia versa tumultus"
    },
    {
      "n": 6,
      "latin": "adsimilare freto possis, quod saeva quietum"
    },
    {
      "n": 7,
      "latin": "ventorum rabies motis exasperat undis."
    },
    {
      "n": 8,
      "latin": "Primus in his Phineus, belli temerarius auctor,"
    },
    {
      "n": 9,
      "latin": "fraxineam quatiens aeratae cuspidis hastam,"
    },
    {
      "n": 10,
      "latin": "“en” ait, “en adsum praereptae coniugis ultor,"
    },
    {
      "n": 11,
      "latin": "nec mihi te pennae, nec falsum versus in aurum"
    },
    {
      "n": 12,
      "latin": "Iuppiter eripiet.” Conanti mittere Cepheus"
    },
    {
      "n": 13,
      "latin": "“quid facis?” exclamat, “quae te, germane, furentem"
    },
    {
      "n": 14,
      "latin": "mens agit in facinus? meritisne haec gratia tantis"
    },
    {
      "n": 15,
      "latin": "redditur? hac vitam servatae dote rependis?"
    },
    {
      "n": 16,
      "latin": "Quam tibi non Perseus, verum si quaeris, ademit,"
    },
    {
      "n": 17,
      "latin": "sed grave Nereidum numen, sed corniger Ammon,"
    },
    {
      "n": 18,
      "latin": "sed quae visceribus veniebat belua ponti"
    },
    {
      "n": 19,
      "latin": "exsaturanda meis. Illo tibi tempore rapta est,"
    },
    {
      "n": 20,
      "latin": "quo peritura fuit: nisi si crudelis id ipsum"
    },
    {
      "n": 21,
      "latin": "exigis, ut pereat, luctuque levabere nostro."
    },
    {
      "n": 22,
      "latin": "Scilicet haud satis est, quod te spectante revincta est"
    },
    {
      "n": 23,
      "latin": "et nullam quod opem patruus sponsusve tulisti:"
    },
    {
      "n": 24,
      "latin": "insuper, a quoquam quod sit servata, dolebis"
    },
    {
      "n": 25,
      "latin": "praemiaque eripies? Quae si tibi magna videntur,"
    },
    {
      "n": 26,
      "latin": "ex illis scopulis, ubi erant adfixa, petisses."
    },
    {
      "n": 27,
      "latin": "Nunc sine, qui petiit, per quem haec non orba senectus,"
    },
    {
      "n": 28,
      "latin": "ferre quod et meritis et voce est pactus, eumque"
    },
    {
      "n": 29,
      "latin": "non tibi, sed certae praelatum intellege morti!”"
    },
    {
      "n": 30,
      "latin": "Ille nihil contra: sed et hunc et Persea vultu"
    },
    {
      "n": 31,
      "latin": "alterno spectans petat hunc ignorat, an illum,"
    },
    {
      "n": 32,
      "latin": "cunctatusque brevi contortam viribus hastam,"
    },
    {
      "n": 33,
      "latin": "quantas ira dabat, nequiquam in Persea misit."
    },
    {
      "n": 34,
      "latin": "Ut stetit illa toro, stratis tunc denique Perseus"
    },
    {
      "n": 35,
      "latin": "exsiluit; teloque ferox inimica remisso"
    },
    {
      "n": 36,
      "latin": "pectora rupisset, nisi post altaria Phineus"
    },
    {
      "n": 37,
      "latin": "isset: et (indignum!) scelerato profuit ara."
    },
    {
      "n": 38,
      "latin": "Fronte tamen Rhoeti non inrita cuspis adhaesit."
    },
    {
      "n": 39,
      "latin": "Qui postquam cecidit ferrumque ex osse revulsum est,"
    },
    {
      "n": 40,
      "latin": "calcitrat et positas adspergit sanguine mensas."
    },
    {
      "n": 41,
      "latin": "Tum vero indomitas ardescit vulgus in iras,"
    },
    {
      "n": 42,
      "latin": "telaque coniciunt, et sunt, qui Cephea dicunt"
    },
    {
      "n": 43,
      "latin": "cum genero debere mori. Sed limine tecti"
    },
    {
      "n": 44,
      "latin": "exierat Cepheus, testatus iusque fidemque"
    },
    {
      "n": 45,
      "latin": "hospitiique deos, ea se prohibente moveri."
    },
    {
      "n": 46,
      "latin": "Bellica Pallas adest et protegit aegide fratrem"
    },
    {
      "n": 47,
      "latin": "datque animos. Erat Indus Athis, quem flumine Gange"
    },
    {
      "n": 48,
      "latin": "edita Limnaee vitreis peperisse sub undis"
    },
    {
      "n": 49,
      "latin": "creditur, egregius forma, quam divite cultu"
    },
    {
      "n": 50,
      "latin": "augebat, bis adhuc octonis integer annis,"
    },
    {
      "n": 51,
      "latin": "indutus chlamydem Tyriam, quam limbus obibat"
    },
    {
      "n": 52,
      "latin": "aureus; ornabant aurata monilia collum"
    },
    {
      "n": 53,
      "latin": "et madidos murra curvum crinale capillos."
    },
    {
      "n": 54,
      "latin": "Ille quidem iaculo quamvis distantia misso"
    },
    {
      "n": 55,
      "latin": "figere doctus erat, sed tendere doctior arcus."
    },
    {
      "n": 56,
      "latin": "Tunc quoque lenta manu flectentem cornua Perseus"
    },
    {
      "n": 57,
      "latin": "stipite, qui media positus fumabat in ara,"
    },
    {
      "n": 58,
      "latin": "perculit et fractis confudit in ossibus ora."
    },
    {
      "n": 59,
      "latin": "Hunc ubi laudatos iactantem in sanguine vultus"
    },
    {
      "n": 60,
      "latin": "Assyrius vidit Lycabas, iunctissimus illi"
    },
    {
      "n": 61,
      "latin": "et comes et veri non dissimulator amoris,"
    },
    {
      "n": 62,
      "latin": "postquam exhalantem sub acerbo vulnere vitam"
    },
    {
      "n": 63,
      "latin": "deploravit Athin, quos ille tetenderat arcus"
    },
    {
      "n": 64,
      "latin": "arripit et “mecum tibi sint certamina” dixit:"
    },
    {
      "n": 65,
      "latin": "“nec longum pueri fato laetabere, quo plus"
    },
    {
      "n": 66,
      "latin": "invidiae, quam laudis habes.” Haec omnia nondum"
    },
    {
      "n": 67,
      "latin": "dixerat, emicuit nervo penetrabile telum"
    },
    {
      "n": 68,
      "latin": "vitatumque tamen sinuosa veste pependit."
    },
    {
      "n": 69,
      "latin": "Vertit in hunc harpen spectatam caede Medusae"
    },
    {
      "n": 70,
      "latin": "Acrisioniades adigitque in pectus: at ille"
    },
    {
      "n": 71,
      "latin": "iam moriens, oculis sub nocte natantibus atra"
    },
    {
      "n": 72,
      "latin": "circumspexit Athin seque acclinavit ad illum"
    },
    {
      "n": 73,
      "latin": "et tulit ad manes iunctae solacia mortis."
    }
  ]
}
