{
  "id": "adhaereo_v",
  "lemma": "adhaereo",
  "pos": "verb",
  "glosses": [
    "adhere, stick, cling/cleave to",
    "hang on",
    "be attached/concerned/involved"
  ],
  "reviewed": false,
  "head": "adhaereo, adhaerere, adhaesi, adhaesum",
  "principal_parts": [
    "adhaereo",
    "adhaerere",
    "adhaesi",
    "adhaesum"
  ],
  "paradigm": {
    "type": "verb",
    "rows": [
      "1sg",
      "2sg",
      "3sg",
      "1pl",
      "2pl",
      "3pl"
    ],
    "cols": [
      "pres.ind.act",
      "imperf.ind.act",
      "fut.ind.act",
      "perf.ind.act",
      "pres.subj.act",
      "imperf.subj.act",
      "pres.imp.act",
      "pres.ind.pass",
      "imperf.ind.pass",
      "fut.ind.pass"
    ],
    "cells": {
      "1sg.pres.ind.act": "adhaereo",
      "2sg.pres.ind.act": "adhaeres",
      "3sg.pres.ind.act": "adhaeret",
      "1pl.pres.ind.act": "adhaeremus",
      "2pl.pres.ind.act": "adhaeretis",
      "3pl.pres.ind.act": "adhaerent",
      "1sg.imperf.ind.act": "adhaerebam",
      "2sg.imperf.ind.act": "adhaerebas",
      "3sg.imperf.ind.act": "adhaerebat",
      "1pl.imperf.ind.act": "adhaerebamus",
      "2pl.imperf.ind.act": "adhaerebatis",
      "3pl.imperf.ind.act": "adhaerebant",
      "1sg.fut.ind.act": "adhaerebo",
      "2sg.fut.ind.act": "adhaerebis",
      "3sg.fut.ind.act": "adhaerebit",
      "1pl.fut.ind.act": "adhaerebimus",
      "2pl.fut.ind.act": "adhaerebitis",
      "3pl.fut.ind.act": "adhaerebunt",
      "1sg.pres.ind.pass": "adhaereor",
      "2sg.pres.ind.pass": "adhaereris",
      "3sg.pres.ind.pass": "adhaeretur",
      "1pl.pres.ind.pass": "adhaeremur",
      "2pl.pres.ind.pass": "adhaeremini",
      "3pl.pres.ind.pass": "adhaerentur",
      "1sg.imperf.ind.pass": "adhaerebar",
      "2sg.imperf.ind.pass": "adhaerebaris",
      "3sg.imperf.ind.pass": "adhaerebatur",
      "1pl.imperf.ind.pass": "adhaerebamur",
      "2pl.imperf.ind.pass": "adhaerebamini",
      "3pl.imperf.ind.pass": "adhaerebantur",
      "1sg.fut.ind.pass": "adhaerebor",
      "2sg.fut.ind.pass": "adhaereberis",
      "3sg.fut.ind.pass": "adhaerebitur",
      "1pl.fut.ind.pass": "adhaerebimur",
      "2pl.fut.ind.pass": "adhaerebimini",
      "3pl.fut.ind.pass": "adhaerebuntur",
      "1sg.pres.subj.act": "adhaeream",
      "2sg.pres.subj.act": "adhaereas",
      "3sg.pres.subj.act": "adhaereat",
      "1pl.pres.subj.act": "adhaereamus",
      "2pl.pres.subj.act": "adhaereatis",
      "3pl.pres.subj.act": "adhaereant",
      "1sg.imperf.subj.act": "adhaererem",
      "2sg.imperf.subj.act": "adhaereres",
      "3sg.imperf.subj.act": "adhaereret",
      "1pl.imperf.subj.act": "adhaereremus",
      "2pl.imperf.subj.act": "adhaereretis",
      "3pl.imperf.subj.act": "adhaererent",
      "2sg.pres.imp.act": "adhaere",
      "2pl.pres.imp.act": "adhaerete",
      "1sg.perf.ind.act": "adhaesi",
      "2sg.perf.ind.act": "adhaesisti",
      "3sg.perf.ind.act": "adhaesit",
      "1pl.perf.ind.act": "adhaesimus",
      "2pl.perf.ind.act": "adhaesistis",
      "3pl.perf.ind.act": "adhaeserunt"
    }
  },
  "ppp_paradigm": {
    "label": "PPP: adhaesus -a -um",
    "type": "ppp",
    "rows": [
      "nom",
      "gen",
      "dat",
      "acc",
      "abl",
      "voc"
    ],
    "cols": [
      "sg.masc",
      "sg.fem",
      "sg.neut",
      "pl.masc",
      "pl.fem",
      "pl.neut"
    ],
    "cells": {
      "ppp.nom.sg.masc": "adhaesus",
      "ppp.nom.sg.fem": "adhaesa",
      "ppp.nom.sg.neut": "adhaesum",
      "ppp.gen.sg.masc": "adhaesi",
      "ppp.gen.sg.fem": "adhaesae",
      "ppp.gen.sg.neut": "adhaesi",
      "ppp.dat.sg.masc": "adhaeso",
      "ppp.dat.sg.fem": "adhaesae",
      "ppp.dat.sg.neut": "adhaeso",
      "ppp.acc.sg.masc": "adhaesum",
      "ppp.acc.sg.fem": "adhaesam",
      "ppp.acc.sg.neut": "adhaesum",
      "ppp.abl.sg.masc": "adhaeso",
      "ppp.abl.sg.fem": "adhaesa",
      "ppp.abl.sg.neut": "adhaeso",
      "ppp.voc.sg.masc": "adhaese",
      "ppp.voc.sg.fem": "adhaesa",
      "ppp.voc.sg.neut": "adhaesum",
      "ppp.nom.pl.masc": "adhaesi",
      "ppp.nom.pl.fem": "adhaesae",
      "ppp.nom.pl.neut": "adhaesa",
      "ppp.gen.pl.masc": "adhaesorum",
      "ppp.gen.pl.fem": "adhaesarum",
      "ppp.gen.pl.neut": "adhaesorum",
      "ppp.dat.pl.masc": "adhaesis",
      "ppp.dat.pl.fem": "adhaesis",
      "ppp.dat.pl.neut": "adhaesis",
      "ppp.acc.pl.masc": "adhaesos",
      "ppp.acc.pl.fem": "adhaesas",
      "ppp.acc.pl.neut": "adhaesa",
      "ppp.abl.pl.masc": "adhaesis",
      "ppp.abl.pl.fem": "adhaesis",
      "ppp.abl.pl.neut": "adhaesis",
      "ppp.voc.pl.masc": "adhaesi",
      "ppp.voc.pl.fem": "adhaesae",
      "ppp.voc.pl.neut": "adhaesa"
    }
  }
}
