{
  "id": "custos_n",
  "lemma": "custos",
  "pos": "noun",
  "glosses": [
    "guard",
    "sentry/watch",
    "guardian/protector/keeper",
    "doorkeeper/watchman/janitor",
    "jailer, warden",
    "poll watcher"
  ],
  "head": "custos, -is, c.",
  "paradigm": {
    "type": "noun",
    "rows": [
      "nom",
      "gen",
      "dat",
      "acc",
      "abl"
    ],
    "cols": [
      "sg",
      "pl"
    ],
    "cells": {
      "acc.sg": "custodem",
      "gen.pl": "custodum",
      "acc.pl": "custodis",
      "nom.sg": "custos",
      "gen.sg": "custodis",
      "dat.sg": "custodi",
      "abl.sg": "custode",
      "nom.pl": "custodes",
      "dat.pl": "custodibus",
      "abl.pl": "custodibus"
    }
  }
}
