{
  "id": "navigo_v",
  "lemma": "navigo",
  "pos": "verb",
  "glosses": [
    "sail",
    "navigate"
  ],
  "head": "navigo, navigare, navigavi, navigatum",
  "principal_parts": [
    "navigo",
    "navigare",
    "navigavi",
    "navigatum"
  ],
  "paradigm": {
    "type": "verb",
    "rows": [
      "1sg",
      "2sg",
      "3sg",
      "1pl",
      "2pl",
      "3pl"
    ],
    "cols": [
      "pres.ind.act",
      "imperf.ind.act",
      "fut.ind.act",
      "perf.ind.act",
      "pres.subj.act",
      "imperf.subj.act",
      "pres.imp.act",
      "pres.ind.pass",
      "imperf.ind.pass",
      "fut.ind.pass"
    ],
    "cells": {
      "1sg.pres.ind.act": "navigo",
      "2sg.pres.ind.act": "navigas",
      "3sg.pres.ind.act": "navigat",
      "1pl.pres.ind.act": "navigamus",
      "2pl.pres.ind.act": "navigatis",
      "3pl.pres.ind.act": "navigant",
      "1sg.imperf.ind.act": "navigabam",
      "2sg.imperf.ind.act": "navigabas",
      "3sg.imperf.ind.act": "navigabat",
      "1pl.imperf.ind.act": "navigabamus",
      "2pl.imperf.ind.act": "navigabatis",
      "3pl.imperf.ind.act": "navigabant",
      "1sg.fut.ind.act": "navigabo",
      "2sg.fut.ind.act": "navigabis",
      "3sg.fut.ind.act": "navigabit",
      "1pl.fut.ind.act": "navigabimus",
      "2pl.fut.ind.act": "navigabitis",
      "3pl.fut.ind.act": "navigabunt",
      "1sg.pres.ind.pass": "navigor",
      "2sg.pres.ind.pass": "navigaris",
      "3sg.pres.ind.pass": "navigatur",
      "1pl.pres.ind.pass": "navigamur",
      "2pl.pres.ind.pass": "navigamini",
      "3pl.pres.ind.pass": "navigantur",
      "1sg.imperf.ind.pass": "navigabar",
      "2sg.imperf.ind.pass": "navigabaris",
      "3sg.imperf.ind.pass": "navigabatur",
      "1pl.imperf.ind.pass": "navigabamur",
      "2pl.imperf.ind.pass": "navigabamini",
      "3pl.imperf.ind.pass": "navigabantur",
      "1sg.fut.ind.pass": "navigabor",
      "2sg.fut.ind.pass": "navigaberis",
      "3sg.fut.ind.pass": "navigabitur",
      "1pl.fut.ind.pass": "navigabimur",
      "2pl.fut.ind.pass": "navigabimini",
      "3pl.fut.ind.pass": "navigabuntur",
      "1sg.pres.subj.act": "navigem",
      "2sg.pres.subj.act": "naviges",
      "3sg.pres.subj.act": "naviget",
      "1pl.pres.subj.act": "navigemus",
      "2pl.pres.subj.act": "navigetis",
      "3pl.pres.subj.act": "navigent",
      "1sg.imperf.subj.act": "navigarem",
      "2sg.imperf.subj.act": "navigares",
      "3sg.imperf.subj.act": "navigaret",
      "1pl.imperf.subj.act": "navigaremus",
      "2pl.imperf.subj.act": "navigaretis",
      "3pl.imperf.subj.act": "navigarent",
      "2sg.pres.imp.act": "naviga",
      "2pl.pres.imp.act": "navigate",
      "1sg.perf.ind.act": "navigavi",
      "2sg.perf.ind.act": "navigavisti",
      "3sg.perf.ind.act": "navigavit",
      "1pl.perf.ind.act": "navigavimus",
      "2pl.perf.ind.act": "navigavistis",
      "3pl.perf.ind.act": "navigaverunt"
    }
  },
  "ppp_paradigm": {
    "label": "PPP: navigatus -a -um",
    "type": "ppp",
    "rows": [
      "nom",
      "gen",
      "dat",
      "acc",
      "abl",
      "voc"
    ],
    "cols": [
      "sg.masc",
      "sg.fem",
      "sg.neut",
      "pl.masc",
      "pl.fem",
      "pl.neut"
    ],
    "cells": {
      "ppp.nom.sg.masc": "navigatus",
      "ppp.nom.sg.fem": "navigata",
      "ppp.nom.sg.neut": "navigatum",
      "ppp.gen.sg.masc": "navigati",
      "ppp.gen.sg.fem": "navigatae",
      "ppp.gen.sg.neut": "navigati",
      "ppp.dat.sg.masc": "navigato",
      "ppp.dat.sg.fem": "navigatae",
      "ppp.dat.sg.neut": "navigato",
      "ppp.acc.sg.masc": "navigatum",
      "ppp.acc.sg.fem": "navigatam",
      "ppp.acc.sg.neut": "navigatum",
      "ppp.abl.sg.masc": "navigato",
      "ppp.abl.sg.fem": "navigata",
      "ppp.abl.sg.neut": "navigato",
      "ppp.voc.sg.masc": "navigate",
      "ppp.voc.sg.fem": "navigata",
      "ppp.voc.sg.neut": "navigatum",
      "ppp.nom.pl.masc": "navigati",
      "ppp.nom.pl.fem": "navigatae",
      "ppp.nom.pl.neut": "navigata",
      "ppp.gen.pl.masc": "navigatorum",
      "ppp.gen.pl.fem": "navigatarum",
      "ppp.gen.pl.neut": "navigatorum",
      "ppp.dat.pl.masc": "navigatis",
      "ppp.dat.pl.fem": "navigatis",
      "ppp.dat.pl.neut": "navigatis",
      "ppp.acc.pl.masc": "navigatos",
      "ppp.acc.pl.fem": "navigatas",
      "ppp.acc.pl.neut": "navigata",
      "ppp.abl.pl.masc": "navigatis",
      "ppp.abl.pl.fem": "navigatis",
      "ppp.abl.pl.neut": "navigatis",
      "ppp.voc.pl.masc": "navigati",
      "ppp.voc.pl.fem": "navigatae",
      "ppp.voc.pl.neut": "navigata"
    }
  }
}
