{
  "id": "spargo_v",
  "lemma": "spargo",
  "pos": "verb",
  "glosses": [
    "scatter, strew, sprinkle",
    "spot"
  ],
  "head": "spargo, spargere, sparsi, sparsum",
  "principal_parts": [
    "spargo",
    "spargere",
    "sparsi",
    "sparsum"
  ],
  "paradigm": {
    "type": "verb",
    "rows": [
      "1sg",
      "2sg",
      "3sg",
      "1pl",
      "2pl",
      "3pl"
    ],
    "cols": [
      "pres.ind.act",
      "perf.ind.act",
      "imperf.subj.act",
      "pres.imp.act",
      "pres.ind.pass"
    ],
    "cells": {
      "2sg.pres.ind.act": "spargis",
      "3sg.pres.ind.act": "spargit",
      "1pl.pres.ind.act": "spargimus",
      "2pl.pres.ind.act": "spargitis",
      "2sg.pres.ind.pass": "spargeris",
      "3sg.pres.ind.pass": "spargitur",
      "1sg.imperf.subj.act": "spargerem",
      "2sg.imperf.subj.act": "spargeres",
      "3sg.imperf.subj.act": "spargeret",
      "1pl.imperf.subj.act": "spargeremus",
      "2pl.imperf.subj.act": "spargeretis",
      "3pl.imperf.subj.act": "spargerent",
      "2sg.pres.imp.act": "sparge",
      "2pl.pres.imp.act": "spargite",
      "1sg.perf.ind.act": "sparsi",
      "2sg.perf.ind.act": "sparsisti",
      "3sg.perf.ind.act": "sparsit",
      "1pl.perf.ind.act": "sparsimus",
      "2pl.perf.ind.act": "sparsistis",
      "3pl.perf.ind.act": "sparserunt"
    }
  },
  "ppp_paradigm": {
    "label": "PPP: sparsus -a -um",
    "type": "ppp",
    "rows": [
      "nom",
      "gen",
      "dat",
      "acc",
      "abl",
      "voc"
    ],
    "cols": [
      "sg.masc",
      "sg.fem",
      "sg.neut",
      "pl.masc",
      "pl.fem",
      "pl.neut"
    ],
    "cells": {
      "ppp.nom.sg.masc": "sparsus",
      "ppp.nom.sg.fem": "sparsa",
      "ppp.nom.sg.neut": "sparsum",
      "ppp.gen.sg.masc": "sparsi",
      "ppp.gen.sg.fem": "sparsae",
      "ppp.gen.sg.neut": "sparsi",
      "ppp.dat.sg.masc": "sparso",
      "ppp.dat.sg.fem": "sparsae",
      "ppp.dat.sg.neut": "sparso",
      "ppp.acc.sg.masc": "sparsum",
      "ppp.acc.sg.fem": "sparsam",
      "ppp.acc.sg.neut": "sparsum",
      "ppp.abl.sg.masc": "sparso",
      "ppp.abl.sg.fem": "sparsa",
      "ppp.abl.sg.neut": "sparso",
      "ppp.voc.sg.masc": "sparse",
      "ppp.voc.sg.fem": "sparsa",
      "ppp.voc.sg.neut": "sparsum",
      "ppp.nom.pl.masc": "sparsi",
      "ppp.nom.pl.fem": "sparsae",
      "ppp.nom.pl.neut": "sparsa",
      "ppp.gen.pl.masc": "sparsorum",
      "ppp.gen.pl.fem": "sparsarum",
      "ppp.gen.pl.neut": "sparsorum",
      "ppp.dat.pl.masc": "sparsis",
      "ppp.dat.pl.fem": "sparsis",
      "ppp.dat.pl.neut": "sparsis",
      "ppp.acc.pl.masc": "sparsos",
      "ppp.acc.pl.fem": "sparsas",
      "ppp.acc.pl.neut": "sparsa",
      "ppp.abl.pl.masc": "sparsis",
      "ppp.abl.pl.fem": "sparsis",
      "ppp.abl.pl.neut": "sparsis",
      "ppp.voc.pl.masc": "sparsi",
      "ppp.voc.pl.fem": "sparsae",
      "ppp.voc.pl.neut": "sparsa"
    }
  }
}
